MANIFEST.in
README.rst
setup.py
mattdaemon/__init__.py
mattdaemon/daemon.py
mattdaemon/example.py
mattdaemon.egg-info/PKG-INFO
mattdaemon.egg-info/SOURCES.txt
mattdaemon.egg-info/dependency_links.txt
mattdaemon.egg-info/not-zip-safe
mattdaemon.egg-info/top_level.txt