Metadata-Version: 1.1
Name: mattdaemon
Version: 1.0.0
Summary: Easily daemonize your python projects
Home-page: https://github.com/plausibility/mattdaemon
Author: plausibility
Author-email: chris@gibsonsec.org
License: MIT
Keywords: daemon daemonize daemonise cli matt
Platform: UNKNOWN
Classifier: Development Status :: 5 - Production/Stable
Classifier: Intended Audience :: Developers
Classifier: License :: OSI Approved :: MIT License
Classifier: Operating System :: POSIX :: Linux
Classifier: Programming Language :: Python :: 2
